streamlit_custom_checkbox/__init__.py
streamlit_custom_checkbox/frontend/build/index.html
streamlit_custom_checkbox/frontend/build/static/js/2.c188ad39.chunk.js
streamlit_custom_checkbox/frontend/build/static/js/main.dde18032.chunk.js
streamlit_custom_checkbox/frontend/build/static/js/runtime-main.30e7a360.js
streamlit_custom_checkbox_rpathak-0.1.0.dist-info/METADATA
streamlit_custom_checkbox_rpathak-0.1.0.dist-info/WHEEL
streamlit_custom_checkbox_rpathak-0.1.0.dist-info/top_level.txt
streamlit_custom_checkbox_rpathak-0.1.0.dist-info/RECORD
