Metadata-Version: 2.1
Name: streamlit-custom-checkbox-rpathak
Version: 0.1.0
Summary: A custom checkbox component for Streamlit
Home-page: https://github.com/rpathak/streamlit-custom-checkbox-rpathak
Author: Your Name
Author-email: your.email@example.com
Classifier: Programming Language :: Python :: 3
Classifier: License :: OSI Approved :: MIT License
Classifier: Operating System :: OS Independent
Requires-Python: >=3.6
Requires-Dist: streamlit>=0.63
